fofa/__init__.py
fofa/__main__.py
FofaCli-1.0.0.dist-info/LICENSE
FofaCli-1.0.0.dist-info/METADATA
FofaCli-1.0.0.dist-info/WHEEL
FofaCli-1.0.0.dist-info/entry_points.txt
FofaCli-1.0.0.dist-info/top_level.txt
FofaCli-1.0.0.dist-info/RECORD
