Metadata-Version: 2.1
Name: FofaCli
Version: 1.0.0
Summary: Command-line interaction tools for fofa.info
Home-page: https://github.com/0x4d0/FofaCli
Author: 0x4d0
Author-email: bello.abcx@gmail.com
License: MIT Licence
Platform: UNKNOWN
Classifier: Development Status :: 7 - Inactive
Classifier: License :: OSI Approved :: Apache Software License
Classifier: Operating System :: OS Independent
Classifier: Programming Language :: Python :: 3
Classifier: Programming Language :: Python :: 3.6
Classifier: Programming Language :: Python :: 3.7
Classifier: Programming Language :: Python :: 3.8
Classifier: Programming Language :: Python :: 3.9
Classifier: Programming Language :: Python :: 3.10
License-File: LICENSE
Requires-Dist: beautifultable (==1.1.0)
Requires-Dist: prompt-toolkit (==3.0.29)
Requires-Dist: pycryptodomex (==3.15.0)
Requires-Dist: requests (==2.26.0)
Requires-Dist: rich (==12.5.1)
Requires-Dist: termcolor (==1.1.0)
